rj_api/__init__.py
rj_api/base_request.py
rj_api/media.py
rj_api/user_auth.py
python_rj_app-0.1.1.dist-info/METADATA
python_rj_app-0.1.1.dist-info/WHEEL
python_rj_app-0.1.1.dist-info/top_level.txt
python_rj_app-0.1.1.dist-info/RECORD
