Metadata-Version: 2.1
Name: python-rj-app
Version: 0.1.1
Summary: Radio Javan Python Binding
Home-page: https://github.com/sauditore/radio-javan
Author: Amir Pourjafari
Author-email: amir.pourjafari@gmail.com
License: UNKNOWN
Project-URL: Bug Tracker, https://github.com/sauditore/radio-javan/issues
Platform: UNKNOWN
Classifier: Programming Language :: Python :: 3
Classifier: License :: OSI Approved :: MIT License
Classifier: Operating System :: OS Independent
Requires-Python: >=3.6
Requires-Dist: requests
Requires-Dist: bs4
